fasthandler/__init__.py
fasthandler/errors/__init__.py
fasthandler/errors/baseerror.py
fasthandler/errors/customexception.py
fasthandler/handlers/__init__.py
fasthandler/handlers/customerrorhandler.py
fasthandler/handlers/generalerrorhandler.py
fasthandler/handlers/jwterrorhandler.py
fasthandler/handlers/mongoerrorhandler.py
fasthandler/handlers/registry.py
fasthandler/middleware/__init__.py
fasthandler/middleware/middlewareregistry.py
fasthandler/utils/__init__.py
fasthandler/utils/mongo_validations.py
coretus_common-0.1.18.dist-info/METADATA
coretus_common-0.1.18.dist-info/WHEEL
coretus_common-0.1.18.dist-info/top_level.txt
coretus_common-0.1.18.dist-info/RECORD
